assets/__init__.py
assets/app_settings.py
assets/apps.py
assets/auth_hooks.py
assets/decorators.py
assets/errors.py
assets/hooks.py
assets/managers.py
assets/models.py
assets/providers.py
assets/tasks.py
assets/urls.py
assets/views.py
assets/api/__init__.py
assets/api/schema.py
assets/api/assets/__init__.py
assets/api/assets/assets.py
assets/api/requests/__init__.py
assets/api/requests/requests.py
assets/locale/de/LC_MESSAGES/django.mo
assets/locale/de/LC_MESSAGES/django.po
assets/migrations/0001_initial.py
assets/migrations/0002_alter_request_status.py
assets/migrations/__init__.py
assets/static/assets/js/assets.js
assets/static/assets/js/requests.js
assets/task_helpers/__init__.py
assets/task_helpers/etag_helpers.py
assets/task_helpers/location_helpers.py
assets/templates/assets/assets.html
assets/templates/assets/base.html
assets/templates/assets/index.html
assets/templates/assets/requests.html
assets/templates/assets/js/assets-js.html
assets/templates/assets/js/requests-js.html
assets/templates/assets/partials/administration.html
assets/templates/assets/partials/navigation.html
assets/tests/__init__.py
assets/tests/test_views.py
aa_assets-0.1.2.dist-info/METADATA
aa_assets-0.1.2.dist-info/WHEEL
aa_assets-0.1.2.dist-info/licenses/LICENSE
aa_assets-0.1.2.dist-info/RECORD
