Metadata-Version: 2.3
Name: aa-assets
Version: 0.1.2
Summary: Character and Corporation statistics, including detailed information on ESS, Ratting, Trading, Mining, and other activities.
Project-URL: Changelog, https://github.com/Geuthur/aa-assets/blob/master/CHANGELOG.md
Project-URL: Homepage, https://github.com/Geuthur/aa-assets
Project-URL: Source, https://github.com/Geuthur/aa-assets
Project-URL: Tracker, https://github.com/Geuthur/aa-assets/issues
Author-email: Geuthur <devgeuthur@gmail.com>
License:                     GNU GENERAL PUBLIC LICENSE
License-File: LICENSE
Classifier: Environment :: Web Environment
Classifier: Framework :: Django
Classifier: Framework :: Django :: 4.0
Classifier: Framework :: Django :: 4.2
Classifier: Intended Audience :: Developers
Classifier: License :: OSI Approved :: MIT License
Classifier: Operating System :: OS Independent
Classifier: Programming Language :: Python
Classifier: Programming Language :: Python :: 3 :: Only
Classifier: Programming Language :: Python :: 3.10
Classifier: Programming Language :: Python :: 3.11
Classifier: Programming Language :: Python :: 3.12
Classifier: Topic :: Internet :: WWW/HTTP
Classifier: Topic :: Internet :: WWW/HTTP :: Dynamic Content
Requires-Python: >=3.10
Requires-Dist: allianceauth-app-utils>=1.19
Requires-Dist: allianceauth>=4
Requires-Dist: django-eveuniverse>=1.3
Requires-Dist: django-ninja
Provides-Extra: tests-allianceauth-latest
Requires-Dist: coverage; extra == 'tests-allianceauth-latest'
Requires-Dist: django-webtest; extra == 'tests-allianceauth-latest'
